aebo/__init__.py
aebo-0.9.dist-info/METADATA
aebo-0.9.dist-info/WHEEL
aebo-0.9.dist-info/top_level.txt
aebo-0.9.dist-info/RECORD
